MANIFEST.in
README.md
setup.py
arartekomaps/__init__.py
arartekomaps/manage.py
arartekomaps/models.py
arartekomaps/settings.py
arartekomaps/urls.py
arartekomaps/views.py
arartekomaps/wsgi.py
arartekomaps.egg-info/PKG-INFO
arartekomaps.egg-info/SOURCES.txt
arartekomaps.egg-info/dependency_links.txt
arartekomaps.egg-info/entry_points.txt
arartekomaps.egg-info/not-zip-safe
arartekomaps.egg-info/requires.txt
arartekomaps.egg-info/top_level.txt
arartekomaps/api/__init__.py
arartekomaps/api/handlers.py
arartekomaps/api/urls.py
arartekomaps/arartekouser/__init__.py
arartekomaps/arartekouser/admin.py
arartekomaps/arartekouser/forms.py
arartekomaps/arartekouser/models.py
arartekomaps/arartekouser/translation.py
arartekomaps/categories/__init__.py
arartekomaps/categories/models.py
arartekomaps/categories/translation.py
arartekomaps/initial_data/biblio.csv
arartekomaps/initial_data/transport.csv
arartekomaps/locale/en/LC_MESSAGES/django.mo
arartekomaps/locale/en/LC_MESSAGES/django.po
arartekomaps/locale/es/LC_MESSAGES/django.mo
arartekomaps/locale/es/LC_MESSAGES/django.po
arartekomaps/locale/eu/LC_MESSAGES/django.mo
arartekomaps/locale/eu/LC_MESSAGES/django.po
arartekomaps/locations/__init__.py
arartekomaps/locations/admin.py
arartekomaps/locations/herriak.csv
arartekomaps/locations/models.py
arartekomaps/locations/tests.py
arartekomaps/locations/uploadr.py
arartekomaps/locations/urls.py
arartekomaps/locations/utils.py
arartekomaps/locations/views.py
arartekomaps/locations/widgets.py
arartekomaps/management/__init__.py
arartekomaps/management/commands/__init__.py
arartekomaps/management/commands/count_items.py
arartekomaps/management/commands/delete_not_modified_places.py
arartekomaps/management/commands/export_places.py
arartekomaps/management/commands/lat_lon_list.py
arartekomaps/management/commands/load_biblio_ltln.py
arartekomaps/management/commands/load_places.py
arartekomaps/management/commands/load_places_biblio.py
arartekomaps/management/commands/load_places_elkartu.py
arartekomaps/management/commands/load_places_hotel.py
arartekomaps/management/commands/load_places_infos.py
arartekomaps/management/commands/load_places_rest.py
arartekomaps/management/commands/load_places_transport.py
