Metadata-Version: 1.0
Name: arartekomaps
Version: 5.95
Summary: Django application serving mapak.ararteko.net 
Home-page: https://github.com/ararteko/arartekomaps
Author: Gari Araolaza
Author-email: garaolaza@codesyntax.com
License: GPL
Keywords: maps
Platform: UNKNOWN
